asciimatics/__init__.py
asciimatics/constants.py
asciimatics/effects.py
asciimatics/event.py
asciimatics/exceptions.py
asciimatics/parsers.py
asciimatics/particles.py
asciimatics/paths.py
asciimatics/scene.py
asciimatics/screen.py
asciimatics/sprites.py
asciimatics/strings.py
asciimatics/utilities.py
asciimatics/version.py
asciimatics/renderers/__init__.py
asciimatics/renderers/base.py
asciimatics/renderers/box.py
asciimatics/renderers/charts.py
asciimatics/renderers/figlettext.py
asciimatics/renderers/fire.py
asciimatics/renderers/images.py
asciimatics/renderers/kaleidoscope.py
asciimatics/renderers/plasma.py
asciimatics/renderers/players.py
asciimatics/renderers/rainbow.py
asciimatics/renderers/rotatedduplicate.py
asciimatics/renderers/scales.py
asciimatics/renderers/speechbubble.py
asciimatics/widgets/__init__.py
asciimatics/widgets/baselistbox.py
asciimatics/widgets/button.py
asciimatics/widgets/checkbox.py
asciimatics/widgets/datepicker.py
asciimatics/widgets/divider.py
asciimatics/widgets/dropdownlist.py
asciimatics/widgets/filebrowser.py
asciimatics/widgets/frame.py
asciimatics/widgets/label.py
asciimatics/widgets/layout.py
asciimatics/widgets/listbox.py
asciimatics/widgets/multicolumnlistbox.py
asciimatics/widgets/popupdialog.py
asciimatics/widgets/popupmenu.py
asciimatics/widgets/radiobuttons.py
asciimatics/widgets/scrollbar.py
asciimatics/widgets/temppopup.py
asciimatics/widgets/text.py
asciimatics/widgets/textbox.py
asciimatics/widgets/timepicker.py
asciimatics/widgets/utilities.py
asciimatics/widgets/verticaldivider.py
asciimatics/widgets/widget.py
asciimatics-1.15.0.dist-info/LICENSE
asciimatics-1.15.0.dist-info/METADATA
asciimatics-1.15.0.dist-info/WHEEL
asciimatics-1.15.0.dist-info/top_level.txt
asciimatics-1.15.0.dist-info/RECORD
