Metadata-Version: 2.1
Name: asciimatics
Version: 1.15.0
Summary: A cross-platform package to replace curses (mouse/keyboard input & text colours/positioning) and create ASCII animations
Home-page: https://github.com/peterbrittain/asciimatics
Author: Peter Brittain
Author-email: peter.brittain.os@gmail.com
License: Apache 2.0
Keywords: ascii ansi art credits titles animation curses ncurses windows xterm mouse keyboard terminal tty color colour crossplatform console
Classifier: Development Status :: 5 - Production/Stable
Classifier: Environment :: Console
Classifier: Environment :: Console :: Curses
Classifier: Intended Audience :: Developers
Classifier: Topic :: Text Processing :: General
Classifier: License :: OSI Approved :: Apache Software License
Classifier: Operating System :: OS Independent
Classifier: Programming Language :: Python
Classifier: Programming Language :: Python :: 3
Classifier: Programming Language :: Python :: 3.9
Classifier: Programming Language :: Python :: 3.10
Classifier: Programming Language :: Python :: 3.11
Classifier: Programming Language :: Python :: Implementation :: CPython
Classifier: Programming Language :: Python :: Implementation :: PyPy
Classifier: Topic :: Software Development :: User Interfaces
Classifier: Topic :: Terminals
Requires-Python: >= 3.8
License-File: LICENSE
Requires-Dist: pyfiglet>=0.7.2
Requires-Dist: Pillow>=2.7.0
Requires-Dist: wcwidth
Requires-Dist: pywin32; sys_platform == "win32"
